address/__init__.py
address/admin.py
address/apps.py
address/compat.py
address/forms.py
address/migrations/0001_initial.py
address/migrations/0002_auto_20160213_1726.py
address/migrations/0003_auto_20200830_1851.py
address/migrations/__init__.py
address/models.py
address/static/address/js/address.js
address/static/js/jquery.geocomplete.js
address/static/js/jquery.geocomplete.min.js
address/tests/__init__.py
address/tests/test_forms.py
address/tests/test_models.py
address/widgets.py
setup.cfg
django_address-0.2.6.dist-info/LICENSE
django_address-0.2.6.dist-info/WHEEL
django_address-0.2.6.dist-info/METADATA
django_address-0.2.6.dist-info/RECORD
