Metadata-Version: 2.1
Name: django-address
Version: 0.2.6
Summary: A django application for describing addresses.
Home-page: https://github.com/furious-luke/django-address
License: BSD
Author: Luke Hodkinson
Author-email: furious.luke@gmail.com
Requires-Python: >=3.5
Classifier: Development Status :: 3 - Alpha
Classifier: Framework :: Django
Classifier: Framework :: Django :: 2.2
Classifier: Framework :: Django :: 3.0
Classifier: Intended Audience :: Developers
Classifier: License :: OSI Approved :: BSD License
Classifier: License :: Other/Proprietary License
Classifier: Natural Language :: English
Classifier: Operating System :: OS Independent
Classifier: Programming Language :: Python
Classifier: Programming Language :: Python :: 3
Classifier: Programming Language :: Python :: 3.10
Classifier: Programming Language :: Python :: 3.5
Classifier: Programming Language :: Python :: 3.6
Classifier: Programming Language :: Python :: 3.7
Classifier: Programming Language :: Python :: 3.8
Classifier: Programming Language :: Python :: 3.9
Requires-Dist: Django (>=2.1)
Project-URL: Repository, https://github.com/furious-luke/django-address
